core_utils/__init__.py
core_utils/generate_awr.py
core_utils/run_scp.py
core_utils/run_vmstat.py
core_utils/take_awr_snapshot.py
entrypoint/__init__.py
entrypoint/initialize.py
entrypoint/main_class.py
internal_db_management/__init__.py
internal_db_management/db_ops.py
internal_db_management/get_server_details.py
internal_db_management/pwd_handler.py
oracle_utils/__init__.py
oracle_utils/oracle_awr.py
oracle_utils/remote_oracle_db_connector.py
temp/__init__.py
temp/initiator.py
temp/playground.py
ui_management/__init__.py
ui_management/dynamic_logger.py
ui_management/grid.py
ui_management/tk_page_layouts.py
bigtest_automator-1.0.dist-info/LICENSE
bigtest_automator-1.0.dist-info/METADATA
bigtest_automator-1.0.dist-info/WHEEL
bigtest_automator-1.0.dist-info/entry_points.txt
bigtest_automator-1.0.dist-info/top_level.txt
bigtest_automator-1.0.dist-info/RECORD
