Metadata-Version: 2.1
Name: bigtest-automator
Version: 1.0
Summary: A small tool that helps to run and collect performance related metrics such as VMSTAT and AWR. Highly specific to my ORG, might not be useful for general public. SORRY! - Noob.
Home-page: https://github.com/mspuranika/bigtest-automator.git
Author: Shantharam Puranik M
Author-email: shantharam.puranik@ellucian.com
License-File: LICENSE
Requires-Dist: scp
Requires-Dist: paramiko
Requires-Dist: oracledb
